{
    "question": [
        {
            "ID": "41114125247",
            "question": "data.question",
            "responses": [
                {
                    "response": "data.goodResponse",
                    "isTrue": true,
                    "picked": 0,
                    "lastPicked": "new Date()"
                },
                {
                    "response": "data.badResponse1",
                    "isTrue": false,
                    "picked": 0,
                    "lastPicked": "new Date()"
                },
                {
                    "response": "data.badResponse2",
                    "isTrue": false,
                    "picked": 0,
                    "lastPicked": "new Date()"
                }
            ]
        }
    ]
}